LICENSE
MANIFEST.in
README.md
setup.py
cepko/__init__.py
cepko.egg-info/PKG-INFO
cepko.egg-info/SOURCES.txt
cepko.egg-info/dependency_links.txt
cepko.egg-info/requires.txt
cepko.egg-info/top_level.txt