Metadata-Version: 1.1
Name: cepko
Version: 1.0.1
Summary: Communication with CloudSigma's VMs through a virtual serial port
Home-page: https://github.com/cloudsigma/cepko
Author: CloudSigma AG
Author-email: dev-support@cloudsigma.com
License: UNKNOWN
Keywords: cepko,cloud,cloudsigma,serial port,serial,console
Platform: UNKNOWN
Classifier: Programming Language :: Python
Classifier: Programming Language :: Python :: 2
Classifier: Programming Language :: Python :: 3
Classifier: Operating System :: OS Independent
Classifier: Development Status :: 5 - Production/Stable
Classifier: Environment :: Console
Classifier: Intended Audience :: Developers
Classifier: Intended Audience :: System Administrators
Classifier: License :: OSI Approved :: GNU General Public License v3 (GPLv3)
Classifier: Operating System :: POSIX :: BSD
Classifier: Operating System :: POSIX :: Linux
Classifier: Operating System :: Microsoft :: Windows
Classifier: Topic :: Terminals :: Serial
